runner
sharq_server
