Metadata-Version: 1.1
Name: SharQServer
Version: 0.2.0
Summary: An API queuing server based on the SharQ library.
Home-page: https://github.com/plivo/sharq-server
Author: Plivo Team
Author-email: hello@plivo.com
License: The MIT License (MIT)
